mpyc/__init__.py
mpyc/__main__.py
mpyc/asyncoro.py
mpyc/finfields.py
mpyc/fingroups.py
mpyc/gfpx.py
mpyc/gmpy.py
mpyc/mpctools.py
mpyc/numpy.py
mpyc/random.py
mpyc/runtime.py
mpyc/secgroups.py
mpyc/seclists.py
mpyc/sectypes.py
mpyc/statistics.py
mpyc/thresha.py
mpyc_custom-0.10.10.dist-info/LICENSE
mpyc_custom-0.10.10.dist-info/METADATA
mpyc_custom-0.10.10.dist-info/WHEEL
mpyc_custom-0.10.10.dist-info/top_level.txt
mpyc_custom-0.10.10.dist-info/RECORD
