Metadata-Version: 2.1
Name: mpyc-custom
Version: 0.10.10
Summary: MPyC for Multiparty Computation in Python
Author-email: Juniarto Samsudin <juniarto.samsudin@gmail.com>
License: MIT License
Project-URL: documentation, https://mpyc.readthedocs.io
Project-URL: discussions, https://github.com/lschoe/mpyc/discussions
Project-URL: release notes, https://github.com/lschoe/mpyc/releases
Project-URL: homepage, https://www.win.tue.nl/~berry/mpyc/
Project-URL: repository, https://github.com/lschoe/mpyc
Keywords: crypto,cryptography,multiparty computation,MPC,secret sharing,Shamir threshold scheme,pseudorandom secret sharing,PRSS
Classifier: Development Status :: 4 - Beta
Classifier: Environment :: Console
Classifier: Framework :: AsyncIO
Classifier: Framework :: Jupyter
Classifier: Intended Audience :: Developers
Classifier: Intended Audience :: Education
Classifier: Intended Audience :: Information Technology
Classifier: Intended Audience :: Science/Research
Classifier: License :: OSI Approved :: MIT License
Classifier: Operating System :: OS Independent
Classifier: Programming Language :: Python :: 3 :: Only
Classifier: Topic :: Security :: Cryptography
Classifier: Topic :: Software Development :: Libraries :: Application Frameworks
Classifier: Topic :: Software Development :: Libraries :: Python Modules
Classifier: Topic :: System :: Distributed Computing
Requires-Python: >=3.10
License-File: LICENSE
